build/lib/shared_tensor/__init__.py
build/lib/shared_tensor/async_client.py
build/lib/shared_tensor/async_provider.py
build/lib/shared_tensor/async_task.py
build/lib/shared_tensor/client.py
build/lib/shared_tensor/errors.py
build/lib/shared_tensor/jsonrpc.py
build/lib/shared_tensor/provider.py
build/lib/shared_tensor/server.py
build/lib/shared_tensor/utils.py
shared_tensor/__init__.py
shared_tensor/async_client.py
shared_tensor/async_provider.py
shared_tensor/async_task.py
shared_tensor/client.py
shared_tensor/errors.py
shared_tensor/jsonrpc.py
shared_tensor/provider.py
shared_tensor/server.py
shared_tensor/utils.py
shared_tensor-0.1.2.dist-info/licenses/LICENSE
shared_tensor-0.1.2.dist-info/METADATA
shared_tensor-0.1.2.dist-info/WHEEL
shared_tensor-0.1.2.dist-info/entry_points.txt
shared_tensor-0.1.2.dist-info/top_level.txt
shared_tensor-0.1.2.dist-info/RECORD
