Metadata-Version: 2.4
Name: shared-tensor
Version: 0.1.2
Summary: A library for sharing GPU memory objects across processes using IPC mechanisms
Author-email: Athena Team <contact@world-sim-dev.org>
Maintainer-email: Athena Team <contact@world-sim-dev.org>
License-Expression: Apache-2.0
Project-URL: Homepage, https://github.com/world-sim-dev/shared-tensor
Project-URL: Repository, https://github.com/world-sim-dev/shared-tensor
Project-URL: Documentation, https://github.com/world-sim-dev/shared-tensor/wiki
Project-URL: Bug Reports, https://github.com/world-sim-dev/shared-tensor/issues
Project-URL: Changelog, https://github.com/world-sim-dev/shared-tensor/releases
Keywords: gpu,memory,sharing,ipc,inter-process-communication,pytorch,tensorflow,cuda,model-serving,inference,distributed-computing
Classifier: Development Status :: 3 - Alpha
Classifier: Intended Audience :: Developers
Classifier: Intended Audience :: Science/Research
Classifier: Operating System :: POSIX :: Linux
Classifier: Programming Language :: Python :: 3
Classifier: Programming Language :: Python :: 3.8
Classifier: Programming Language :: Python :: 3.9
Classifier: Programming Language :: Python :: 3.10
Classifier: Programming Language :: Python :: 3.11
Classifier: Programming Language :: Python :: 3.12
Classifier: Topic :: Scientific/Engineering :: Artificial Intelligence
Classifier: Topic :: Software Development :: Libraries :: Python Modules
Classifier: Topic :: System :: Hardware :: Symmetric Multi-processing
Requires-Python: >=3.8
License-File: LICENSE
Requires-Dist: torch>=1.12.0
Requires-Dist: numpy>=1.20.0
Requires-Dist: requests>=2.25.0
Provides-Extra: dev
Requires-Dist: pytest>=6.0; extra == "dev"
Requires-Dist: pytest-cov>=2.0; extra == "dev"
Requires-Dist: black>=22.0; extra == "dev"
Requires-Dist: flake8>=4.0; extra == "dev"
Requires-Dist: isort>=5.0; extra == "dev"
Requires-Dist: mypy>=0.950; extra == "dev"
Requires-Dist: pre-commit>=2.0.0; extra == "dev"
Requires-Dist: build>=0.8.0; extra == "dev"
Requires-Dist: twine>=4.0.0; extra == "dev"
Provides-Extra: test
Requires-Dist: pytest>=6.0; extra == "test"
Requires-Dist: pytest-cov>=2.0; extra == "test"
Requires-Dist: pytest-benchmark>=3.0; extra == "test"
Requires-Dist: pytest-asyncio>=0.20.0; extra == "test"
Provides-Extra: docs
Requires-Dist: sphinx>=4.0.0; extra == "docs"
Requires-Dist: sphinx-rtd-theme>=1.0.0; extra == "docs"
Requires-Dist: myst-parser>=0.18.0; extra == "docs"
Dynamic: license-file
